[
    { "id": 0, "quote": "Acredite em si próprio e todo o resto virá naturalmente.", "author": "Desconhecido" },
    { "id": 1, "quote": "O sucesso é a soma de pequenos esforços repetidos dia após dia.", "author": "Robert Collier" },
    { "id": 2, "quote": "Nunca é tarde demais para ser o que você poderia ter sido.", "author": "George Eliot" },
    { "id": 3, "quote": "Você é o único responsável pelo seu sucesso.", "author": "Desconhecido" },
    { "id": 4, "quote": "A única maneira de fazer um ótimo trabalho é amar o que você faz.", "author": "Steve Jobs" },
    { "id": 5, "quote": "Acredite que você pode e você já está no meio do caminho.", "author": "Theodore Roosevelt" },
    { "id": 6, "quote": "A persistência é o caminho do sucesso.", "author": "Charles Chaplin" },
    { "id": 7, "quote": "Se você quer alcançar a grandeza, pare de pedir permissão.", "author": "Desconhecido" },
    { "id": 8, "quote": "O fracasso é simplesmente a oportunidade de começar de novo, desta vez com mais inteligência.", "author": "Henry Ford" },
    { "id": 9, "quote": "Não conte os dias, faça os dias contarem.", "author": "Muhammad Ali" },
    { "id": 10, "quote": "O futuro pertence àqueles que acreditam na beleza de seus sonhos.", "author": "Eleanor Roosevelt" },
    { "id": 11, "quote": "Tudo o que você sempre quis está do outro lado do medo.", "author": "George Addair" },
    { "id": 12, "quote": "Você não encontra a felicidade. Você a cria.", "author": "Desconhecido" },
    { "id": 13, "quote": "O único modo de fazer um excelente trabalho é amar o que você faz.", "author": "Steve Jobs" },
    { "id": 14, "quote": "A vida é o que acontece quando você está ocupado fazendo outros planos.", "author": "John Lennon" },
    { "id": 15, "quote": "A única limitação que você tem é aquela que você coloca em si mesmo.", "author": "Desconhecido" },
    { "id": 16, "quote": "O sucesso é a realização progressiva de um objetivo valioso.", "author": "Earl Nightingale" },
    { "id": 17, "quote": "A diferença entre um vencedor e um perdedor é que o vencedor tenta mais uma vez.", "author": "Desconhecido" },
    { "id": 18, "quote": "Se você não estiver disposto a arriscar o habitual, terá que se contentar com o comum.", "author": "Jim Rohn" },
    { "id": 19, "quote": "O sucesso é a soma de pequenos esforços, repetidos dia após dia.", "author": "Robert Collier" },
    { "id": 20, "quote": "A única maneira de fazer um ótimo trabalho é amar o que você faz.", "author": "Steve Jobs" },
    { "id": 21, "quote": "O maior erro que você pode cometer é ter medo de cometer erros.", "author": "Desconhecido" },
    { "id": 22, "quote": "O sucesso não é a chave para a felicidade. A felicidade é a chave para o sucesso.", "author": "Albert Schweitzer" },
    { "id": 23, "quote": "Você não precisa ser ótimo para começar, mas precisa começar para ser ótimo.", "author": "Zig Ziglar" },
    { "id": 24, "quote": "Nunca desista. Grandes coisas levam tempo.", "author": "Desconhecido" },
    { "id": 25, "quote": "Acredite em si mesmo e todo o resto virá naturalmente.", "author": "Desconhecido" },
    { "id": 26, "quote": "O sucesso é a realização progressiva de um objetivo valioso.", "author": "Earl Nightingale" },
    { "id": 27, "quote": "Não tenha medo de falhar. Tenha medo de não tentar.", "author": "Desconhecido" },
    { "id": 28, "quote": "Você só tem uma vida. Faça dela a melhor possível.", "author": "Desconhecido" },
    { "id": 29, "quote": "O sucesso não é a chave para a felicidade. A felicidade é a chave para o sucesso.", "author": "Albert Schweitzer" },
    { "id": 30, "quote": "A única limitação que você tem é aquela que você coloca em si mesmo.", "author": "Desconhecido" },
    { "id": 31, "quote": "Você não encontra a felicidade. Você a cria.", "author": "Desconhecido" },
    { "id": 32, "quote": "Não conte os dias, faça os dias contarem.", "author": "Muhammad Ali" },
    { "id": 33, "quote": "Se você quer alcançar a grandeza, pare de pedir permissão.", "author": "Desconhecido" },
    { "id": 34, "quote": "Nunca é tarde demais para ser o que você poderia ter sido.", "author": "George Eliot" },
    { "id": 35, "quote": "A persistência é o caminho do sucesso.", "author": "Charles Chaplin" },
    { "id": 36, "quote": "Acredite que você pode e você já está no meio do caminho.", "author": "Theodore Roosevelt" },
    { "id": 37, "quote": "O fracasso é simplesmente a oportunidade de começar de novo, desta vez com mais inteligência.", "author": "Henry Ford" },
    { "id": 38, "quote": "A única maneira de fazer um ótimo trabalho é amar o que você faz.", "author": "Steve Jobs" },
    { "id": 39, "quote": "A vida é o que acontece quando você está ocupado fazendo outros planos.", "author": "John Lennon" },
    { "id": 40, "quote": "A diferença entre um vencedor e um perdedor é que o vencedor tenta mais uma vez.", "author": "Desconhecido" },
    { "id": 41, "quote": "O maior erro que você pode cometer é ter medo de cometer erros.", "author": "Desconhecido" },
    { "id": 42, "quote": "Nunca desista. Grandes coisas levam tempo.", "author": "Desconhecido" },
    { "id": 43, "quote": "O sucesso é a soma de pequenos esforços, repetidos dia após dia.", "author": "Robert Collier" },
    { "id": 44, "quote": "O sucesso é a realização progressiva de um objetivo valioso.", "author": "Earl Nightingale" },
    { "id": 45, "quote": "O único modo de fazer um excelente trabalho é amar o que você faz.", "author": "Steve Jobs" },
    { "id": 46, "quote": "Você só tem uma vida. Faça dela a melhor possível.", "author": "Desconhecido" },
    { "id": 47, "quote": "O futuro pertence àqueles que acreditam na beleza de seus sonhos.", "author": "Eleanor Roosevelt" },
    { "id": 48, "quote": "Tudo o que você sempre quis está do outro lado do medo.", "author": "George Addair" },
    { "id": 49, "quote": "Acreditar em si mesmo é a chave para o sucesso.", "author": "Desconhecido" },
    { "id": 50, "quote": "Não tenha medo de falhar. Tenha medo de não tentar.", "author": "Desconhecido" },
    { "id": 51, "quote": "A única limitação que você tem é aquela que você coloca em si mesmo.", "author": "Desconhecido" },
    { "id": 52, "quote": "A persistência é o caminho do sucesso.", "author": "Charles Chaplin" },
    { "id": 53, "quote": "Acredite que você pode e você já está no meio do caminho.", "author": "Theodore Roosevelt" },
    { "id": 54, "quote": "O sucesso não é a chave para a felicidade. A felicidade é a chave para o sucesso.", "author": "Albert Schweitzer" },
    { "id": 55, "quote": "Você só tem uma vida. Faça dela a melhor possível.", "author": "Desconhecido" },
    { "id": 56, "quote": "Nunca é tarde demais para ser o que você poderia ter sido.", "author": "George Eliot" },
    { "id": 57, "quote": "Não conte os dias, faça os dias contarem.", "author": "Muhammad Ali" },
    { "id": 58, "quote": "O sucesso é a soma de pequenos esforços repetidos dia após dia.", "author": "Robert Collier" },
    { "id": 59, "quote": "Se você não estiver disposto a arriscar o habitual, terá que se contentar com o comum.", "author": "Jim Rohn" },
    { "id": 60, "quote": "Você não precisa ser ótimo para começar, mas precisa começar para ser ótimo.", "author": "Zig Ziglar" },
    { "id": 61, "quote": "A vida é o que acontece quando você está ocupado fazendo outros planos.", "author": "John Lennon" },
    { "id": 62, "quote": "A diferença entre um vencedor e um perdedor é que o vencedor tenta mais uma vez.", "author": "Desconhecido" },
    { "id": 63, "quote": "O maior erro que você pode cometer é ter medo de cometer erros.", "author": "Desconhecido" },
    { "id": 64, "quote": "Nunca desista. Grandes coisas levam tempo.", "author": "Desconhecido" },
    { "id": 65, "quote": "Você não encontra a felicidade. Você a cria.", "author": "Desconhecido" },
    { "id": 66, "quote": "Acredite em si mesmo e todo o resto virá naturalmente.", "author": "Desconhecido" },
    { "id": 67, "quote": "O sucesso é a realização progressiva de um objetivo valioso.", "author": "Earl Nightingale" },
    { "id": 68, "quote": "Você é o único responsável pelo seu sucesso.", "author": "Desconhecido" },
    { "id": 69, "quote": "Nunca é tarde demais para ser o que você poderia ter sido.", "author": "George Eliot" },
    { "id": 70, "quote": "A única limitação que você tem é aquela que você coloca em si mesmo.", "author": "Desconhecido" },
    { "id": 71, "quote": "A diferença entre um vencedor e um perdedor é que o vencedor tenta mais uma vez.", "author": "Desconhecido" },
    { "id": 72, "quote": "Você só tem uma vida. Faça dela a melhor possível.", "author": "Desconhecido" },
    { "id": 73, "quote": "A persistência é o caminho do sucesso.", "author": "Charles Chaplin" },
    { "id": 74, "quote": "O futuro pertence àqueles que acreditam na beleza de seus sonhos.", "author": "Eleanor Roosevelt" },
    { "id": 75, "quote": "Tudo o que você sempre quis está do outro lado do medo.", "author": "George Addair" },
    { "id": 76, "quote": "A vida é o que acontece quando você está ocupado fazendo outros planos.", "author": "John Lennon" },
    { "id": 77, "quote": "Acredite que você pode e você já está no meio do caminho.", "author": "Theodore Roosevelt" },
    { "id": 78, "quote": "O sucesso não é a chave para a felicidade. A felicidade é a chave para o sucesso.", "author": "Albert Schweitzer" },
    { "id": 79, "quote": "Você não encontra a felicidade. Você a cria.", "author": "Desconhecido" },
    { "id": 80, "quote": "O maior erro que você pode cometer é ter medo de cometer erros.", "author": "Desconhecido" },
    { "id": 81, "quote": "A única limitação que você tem é aquela que você coloca em si mesmo.", "author": "Desconhecido" },
    { "id": 82, "quote": "Nunca desista. Grandes coisas levam tempo.", "author": "Desconhecido" },
    { "id": 83, "quote": "A diferença entre um vencedor e um perdedor é que o vencedor tenta mais uma vez.", "author": "Desconhecido" },
    { "id": 84, "quote": "O sucesso é a soma de pequenos esforços repetidos dia após dia.", "author": "Robert Collier" },
    { "id": 85, "quote": "Você é o único responsável pelo seu sucesso.", "author": "Desconhecido" },
    { "id": 86, "quote": "Não tenha medo de falhar. Tenha medo de não tentar.", "author": "Desconhecido" },
    { "id": 87, "quote": "A vida é o que acontece quando você está ocupado fazendo outros planos.", "author": "John Lennon" },
    { "id": 88, "quote": "O futuro pertence àqueles que acreditam na beleza de seus sonhos.", "author": "Eleanor Roosevelt" },
    { "id": 89, "quote": "Você não precisa ser ótimo para começar, mas precisa começar para ser ótimo.", "author": "Zig Ziglar" },
    { "id": 90, "quote": "Tudo o que você sempre quis está do outro lado do medo.", "author": "George Addair" },
    { "id": 91, "quote": "Acredite em si mesmo e todo o resto virá naturalmente.", "author": "Desconhecido" },
    { "id": 92, "quote": "O sucesso é a realização progressiva de um objetivo valioso.", "author": "Earl Nightingale" },
    { "id": 93, "quote": "Nunca é tarde demais para ser o que você poderia ter sido.", "author": "George Eliot" },
    { "id": 94, "quote": "O maior erro que você pode cometer é ter medo de cometer erros.", "author": "Desconhecido" },
    { "id": 95, "quote": "Você só tem uma vida. Faça dela a melhor possível.", "author": "Desconhecido" },
    { "id": 96, "quote": "A persistência é o caminho do sucesso.", "author": "Charles Chaplin" },
    { "id": 97, "quote": "O sucesso não é a chave para a felicidade. A felicidade é a chave para o sucesso.", "author": "Albert Schweitzer" },
    { "id": 98, "quote": "Você não encontra a felicidade. Você a cria.", "author": "Desconhecido" },
    { "id": 99, "quote": "A única limitação que você tem é aquela que você coloca em si mesmo.", "author": "Desconhecido" }
]
